{
    "key": "group_5fe23ee211099",
    "title": "BLOCK: (A) Generic, Headline\/Description",
    "fields": [
        {
            "key": "field_5fe23ef7b1b17",
            "label": "Headline",
            "name": "block_generic_headline",
            "type": "text",
            "instructions": "",
            "required": 1,
            "conditional_logic": 0,
            "wrapper": {
                "width": "",
                "class": "",
                "id": ""
            },
            "default_value": "",
            "placeholder": "Enter your headline text here.",
            "prepend": "",
            "append": "",
            "maxlength": ""
        },
        {
            "key": "field_5fe246ccb1b18",
            "label": "Description",
            "name": "block_generic_description",
            "type": "wysiwyg",
            "instructions": "",
            "required": 0,
            "conditional_logic": 0,
            "wrapper": {
                "width": "",
                "class": "",
                "id": ""
            },
            "default_value": "",
            "tabs": "visual",
            "toolbar": "basic",
            "media_upload": 0,
            "delay": 0
        }
    ],
    "location": [
        [
            {
                "param": "block",
                "operator": "==",
                "value": "acf\/home-snapshot-current"
            }
        ],
        [
            {
                "param": "block",
                "operator": "==",
                "value": "acf\/home-research-themes"
            }
        ],
        [
            {
                "param": "block",
                "operator": "==",
                "value": "acf\/home-sponsored-projects"
            }
        ],
        [
            {
                "param": "block",
                "operator": "==",
                "value": "acf\/home-featured-mentor"
            }
        ],
        [
            {
                "param": "block",
                "operator": "==",
                "value": "acf\/home-featured-project-carousel"
            }
        ]
    ],
    "menu_order": 0,
    "position": "normal",
    "style": "default",
    "label_placement": "top",
    "instruction_placement": "label",
    "hide_on_screen": "",
    "active": true,
    "description": "",
    "modified": 1612482511
}